molecular_string_renderer/__init__.py
molecular_string_renderer/cli.py
molecular_string_renderer/config.py
molecular_string_renderer/core.py
molecular_string_renderer/outputs.py
molecular_string_renderer/parsers.py
molecular_string_renderer/renderers.py
molecular_string_renderer-0.2.0.dist-info/METADATA
molecular_string_renderer-0.2.0.dist-info/WHEEL
molecular_string_renderer-0.2.0.dist-info/entry_points.txt
molecular_string_renderer-0.2.0.dist-info/licenses/LICENSE
molecular_string_renderer-0.2.0.dist-info/RECORD
