Metadata-Version: 2.4
Name: molecular-string-renderer
Version: 0.2.0
Summary: A flexible library for rendering molecular structures from various string representations
Project-URL: Homepage, https://github.com/hunter-heidenreich/molecular-string-renderer
Project-URL: Repository, https://github.com/hunter-heidenreich/molecular-string-renderer
Project-URL: Issues, https://github.com/hunter-heidenreich/molecular-string-renderer/issues
Author-email: Hunter Heidenreich <hunter@hunterheidenreich.com>
License: MIT License
License-File: LICENSE
Keywords: chemistry,molecules,rdkit,smiles,visualization
Classifier: Development Status :: 3 - Alpha
Classifier: Intended Audience :: Science/Research
Classifier: License :: OSI Approved :: MIT License
Classifier: Programming Language :: Python :: 3
Classifier: Programming Language :: Python :: 3.10
Classifier: Programming Language :: Python :: 3.11
Classifier: Programming Language :: Python :: 3.12
Classifier: Topic :: Scientific/Engineering :: Chemistry
Classifier: Topic :: Scientific/Engineering :: Visualization
Requires-Python: >=3.10
Requires-Dist: pillow>=10.0.0
Requires-Dist: pydantic>=2.0.0
Requires-Dist: rdkit
Requires-Dist: reportlab>=4.0.0
Requires-Dist: selfies>=2.2.0
